{
  "meta": {
    "run_dir": "output/run_31sn",
    "airplane_file": "airplane.aero",
    "soln_file": "soln.json"
  },
  "references": {
    "b": 6.826900285302342,
    "S": 2.019120560347396,
    "MAC": 0.30801321808537535,
    "y_boom": 0.8533625356627927,
    "boom_spacing_frac": 0.25,
    "cg_x": 0.091035796655625,
    "operating_altitude_m": 1200.0,
    "temperature_deviation_K": 34.0
  },
  "load_recipes": [
    {
      "name": "positive_g_main_wing_lift",
      "load_type": "force",
      "axis": "z",
      "magnitude_N_or_Nm": 251.86719745183026,
      "distribution": "elliptic_full_span",
      "location": "Applied along main-wing quarter-chord line x = x_LE(y) + 0.25*c(y), for -b/2 <= y <= +b/2.",
      "notes": "Total lift set to L = n_pos * W (n_pos=2.5). Use elliptic L'(y) \u221d sqrt(1-(2y/b)^2)."
    },
    {
      "name": "negative_g_main_wing_lift",
      "load_type": "force",
      "axis": "z",
      "magnitude_N_or_Nm": -100.7468789807321,
      "distribution": "elliptic_full_span",
      "location": "Applied along main-wing quarter-chord line x = x_LE(y) + 0.25*c(y), for -b/2 <= y <= +b/2.",
      "notes": "Total lift set to L = n_neg * W (n_neg=-1.0). Negative indicates downward aerodynamic resultant."
    },
    {
      "name": "rolling_antisymmetric_lift_right",
      "load_type": "force",
      "axis": "z",
      "magnitude_N_or_Nm": "(1+0.35) * (n_roll * W / 2)",
      "distribution": "elliptic_semispan_scaled",
      "location": "Right semi-span only: applied along quarter-chord line for 0 <= y <= +b/2.",
      "notes": "Use a selected roll load factor n_roll (often n_roll = n_pos for worst-case rolling pull). Right semi-span carries (1+k_roll) share; elliptic distribution on the right semispan."
    },
    {
      "name": "rolling_antisymmetric_lift_left",
      "load_type": "force",
      "axis": "z",
      "magnitude_N_or_Nm": "(1-0.35) * (n_roll * W / 2)",
      "distribution": "elliptic_semispan_scaled",
      "location": "Left semi-span only: applied along quarter-chord line for -b/2 <= y <= 0.",
      "notes": "Use a selected roll load factor n_roll. Left semi-span carries (1-k_roll) share; elliptic distribution on the left semispan."
    },
    {
      "name": "aileron_induced_torsion_outboard",
      "load_type": "torque",
      "axis": "Mx",
      "magnitude_N_or_Nm": "T_ail(V,delta_a)  # compute from hinge moment + lift increment offset to shear center",
      "distribution": "uniform_or_triangular_outboard_only",
      "location": "Outboard region only: y_boom < |y| <= b/2, applied about wing shear center / elastic axis.",
      "notes": "Use for outboard wing torsion box sizing. If you do not yet compute T_ail, bound it conservatively."
    },
    {
      "name": "aileron_hinge_actuator_load_local",
      "load_type": "moment",
      "axis": "(about hinge line)",
      "magnitude_N_or_Nm": "H = q_inf * S_a * c_a * C_h  # hinge moment",
      "distribution": "concentrated_at_hinges_and_actuator",
      "location": "Aileron hinge line near rear spar (~70\u201380% chord), at hinge stations and actuator hardpoint.",
      "notes": "Use for bracket, horn, hinge fastener pull-through, and local rib reinforcement sizing."
    },
    {
      "name": "tail_download_to_boom_joints",
      "load_type": "force_and_moment",
      "axis": null,
      "magnitude_N_or_Nm": "H_t = q_inf * S_t * C_Lt ;  M_joint ~= H_t * x_tail",
      "distribution": "concentrated_two_boom_joints",
      "location": "Applied at boom\u2013wing joints at y = \u00b10.8534 m (approx), as vertical shear + pitch moment couple.",
      "notes": "Tail loads act on booms and are reacted at wing joints. Evaluate both maximum tail download and maximum tail upload."
    },
    {
      "name": "battery_inertia_vertical_inboard",
      "load_type": "force",
      "axis": "z",
      "magnitude_N_or_Nm": -91.54424239702244,
      "distribution": "uniform_between_booms",
      "location": "Between-booms region: |y| <= 0.8534 m, applied at battery bay centroid (use quarter-chord unless better known).",
      "notes": "Inertial load on structure for +n_z acts downward. Used n_batt_vert=2.5."
    },
    {
      "name": "battery_inertia_longitudinal_inboard",
      "load_type": "force",
      "axis": "x",
      "magnitude_N_or_Nm": 18.30884847940449,
      "distribution": "uniform_between_booms",
      "location": "Between-booms region: |y| <= 0.8534 m, applied at battery bay centroid.",
      "notes": "Forward (+x) if n_x positive; set sign per your acceleration/braking convention. Used n_batt_long=0.5."
    },
    {
      "name": "battery_inertia_lateral_inboard",
      "load_type": "force",
      "axis": "y",
      "magnitude_N_or_Nm": 18.30884847940449,
      "distribution": "uniform_between_booms",
      "location": "Between-booms region: |y| <= 0.8534 m, applied at battery bay centroid.",
      "notes": "Right (+y) if n_y positive; set sign per your yaw/sideslip convention. Used n_batt_lat=0.5."
    },
    {
      "name": "ground_support_rest",
      "load_type": "force",
      "axis": "z",
      "magnitude_N_or_Nm": 100.7468789807321,
      "distribution": "concentrated_at_contact_points",
      "location": "Applied as upward normal reactions at actual ground contact points (booms/skids/belly/tail bumper), summing to W.",
      "notes": "Static support case. Use n_ground_support=1.0. Wing only sees this indirectly through structure."
    },
    {
      "name": "ground_impact_recovery",
      "load_type": "force",
      "axis": "z",
      "magnitude_N_or_Nm": 302.2406369421963,
      "distribution": "concentrated_at_first_contact_point(s)",
      "location": "Applied as upward impact reaction(s) at first-contact point(s); include asymmetric variant (one side first).",
      "notes": "Pick n_ground_impact based on recovery method. Used n_ground_impact=3.0."
    }
  ]
}